{
    "title": "The new MacBook Pro | Supercharged for pros | Apple",
    "description": "The new MacBook Pro is a beast. Supercharged for pros by the M1 Pro or M1 Max, this… thing delivers extraordinary performance that pushes the boundaries of creativity. And with a stunning Liquid Retina XDR display that’s the best ever in a notebook, there’s no limit to what, or where, you can create. The all-new MacBook Pro. Two sizes, two chips. Let it rip.\n\nLearn more: https://apple.co/3aQFk8p\n\n“Warning” by Martin Wave http://apple.co/MartinWave\n\n#AppleEvent #MacBookPro\n\nWelcome to the official Apple YouTube channel. Here you’ll find news about product launches, tutorials, and other great content. Our more than 160,000 employees are dedicated to making the best products on earth, and to leaving the world better than we found it.",
    "lengthSeconds": "108",
    "viewCount": "9690502",
    "publishDate": "2021-10-18",
    "ownerChannelName": "Apple",
    "videoId": "9tobL8U7dQo",
    "author": {
        "id": "UCE_M8A5yxnLfW0KghEeajjw",
        "name": "Apple",
        "user": "Apple",
        "channel_url": "https://www.youtube.com/channel/UCE_M8A5yxnLfW0KghEeajjw",
        "external_channel_url": "https://www.youtube.com/channel/UCE_M8A5yxnLfW0KghEeajjw",
        "user_url": "http://www.youtube.com/user/Apple",
        "thumbnails": [
            {
                "url": "https://yt3.ggpht.com/ytc/AKedOLSHuGZZN-2jeaRrkNPJEUr9jXEPBYOxH7hs9O286A=s48-c-k-c0x00ffffff-no-rj",
                "width": 48,
                "height": 48
            },
            {
                "url": "https://yt3.ggpht.com/ytc/AKedOLSHuGZZN-2jeaRrkNPJEUr9jXEPBYOxH7hs9O286A=s88-c-k-c0x00ffffff-no-rj",
                "width": 88,
                "height": 88
            },
            {
                "url": "https://yt3.ggpht.com/ytc/AKedOLSHuGZZN-2jeaRrkNPJEUr9jXEPBYOxH7hs9O286A=s176-c-k-c0x00ffffff-no-rj",
                "width": 176,
                "height": 176
            }
        ],
        "verified": true,
        "subscriber_count": 15800000
    },
    "likes": 142982,
    "thumbnails": [
        {
            "url": "https://i.ytimg.com/vi/9tobL8U7dQo/hqdefault.jpg?sqp=-oaymwEbCKgBEF5IVfKriqkDDggBFQAAiEIYAXABwAEG&rs=AOn4CLDf4rqeC-UyUo-YKzMLqobya1cGag",
            "width": 168,
            "height": 94
        },
        {
            "url": "https://i.ytimg.com/vi/9tobL8U7dQo/hqdefault.jpg?sqp=-oaymwEbCMQBEG5IVfKriqkDDggBFQAAiEIYAXABwAEG&rs=AOn4CLCFjPzwVMMFoIDC3DXwKkP68v3c8Q",
            "width": 196,
            "height": 110
        },
        {
            "url": "https://i.ytimg.com/vi/9tobL8U7dQo/hqdefault.jpg?sqp=-oaymwEcCPYBEIoBSFXyq4qpAw4IARUAAIhCGAFwAcABBg==&rs=AOn4CLCidfrSOceDgm3ivdTZvmdrI1eVag",
            "width": 246,
            "height": 138
        },
        {
            "url": "https://i.ytimg.com/vi/9tobL8U7dQo/hqdefault.jpg?sqp=-oaymwEcCNACELwBSFXyq4qpAw4IARUAAIhCGAFwAcABBg==&rs=AOn4CLAmyL_QmWfBwreT14Kb-RcwWblAQg",
            "width": 336,
            "height": 188
        },
        {
            "url": "https://i.ytimg.com/vi/9tobL8U7dQo/maxresdefault.jpg",
            "width": 1920,
            "height": 1080
        }
    ]
}
